docker-push-ssh/__init__.py
docker-push-ssh/cli.py
docker-push-ssh/command.py
docker_push_ssh/__init__.py
docker_push_ssh/cli.py
docker_push_ssh/command.py
docker_push_ssh-0.1.5.data/scripts/docker-push-ssh
docker_push_ssh-0.1.5.dist-info/METADATA
docker_push_ssh-0.1.5.dist-info/RECORD
docker_push_ssh-0.1.5.dist-info/WHEEL
docker_push_ssh-0.1.5.dist-info/top_level.txt
