Metadata-Version: 2.1
Name: docker-push-ssh
Version: 0.1.5
Summary: Push local docker images to your remote servers via ssh without the hassle.
Home-page: https://github.com/coherenceapi/docker-push-ssh
Author: Bryan Thornbury
Author-email: bryan@coherenceapi.com
License: UNKNOWN
Platform: UNKNOWN
Classifier: Programming Language :: Python :: 2.7
Classifier: License :: OSI Approved :: Apache Software License
Classifier: Operating System :: OS Independent
Classifier: Intended Audience :: Developers
Classifier: Intended Audience :: System Administrators
Classifier: Topic :: Software Development :: Build Tools
Classifier: Topic :: Utilities
